[{"id": 0, "text": "faucet", "name": "faucet", "children": [{"id": 1, "text": "normal_faucet", "name": "normal_faucet", "children": [{"id": 2, "text": "switch", "name": "switch", "objs": ["original-10", "original-5", "original-7", "original-6", "original-9", "original-11", "original-15"], "ori_id": 2}, {"id": 3, "text": "frame", "name": "frame", "children": [{"id": 4, "text": "vertical_support", "name": "vertical_support", "objs": ["new-0", "original-8", "original-3", "original-1", "original-2", "original-4"], "ori_id": 10}], "objs": ["new-0", "original-8", "original-3", "original-1", "original-2", "original-4"], "ori_id": 3}, {"id": 5, "text": "spout", "name": "spout", "children": [{"id": 6, "text": "tube", "name": "tube", "objs": ["new-3"], "ori_id": 8}], "objs": ["new-3", "original-21", "original-20", "original-25", "original-17", "original-22"], "ori_id": 4}], "objs": ["original-10", "original-5", "original-7", "original-6", "original-9", "original-11", "original-15", "new-0", "original-8", "original-3", "original-1", "original-2", "original-4", "new-3", "original-21", "original-20", "original-25", "original-17", "original-22"], "ori_id": 1}], "objs": ["original-10", "original-5", "original-7", "original-6", "original-9", "original-11", "original-15", "new-0", "original-8", "original-3", "original-1", "original-2", "original-4", "new-3", "original-21", "original-20", "original-25", "original-17", "original-22"], "ori_id": 0}]