[{"id": 0, "children": [{"id": 1, "children": [{"id": 2, "children": [{"id": 3, "children": [{"ori_id": 51, "id": 4, "name": "board", "text": "board", "objs": ["original-3"]}], "name": "tabletop_surface", "text": "tabletop_surface", "ori_id": 50, "objs": ["original-3"]}], "name": "tabletop", "text": "tabletop", "ori_id": 38, "objs": ["original-3"]}, {"id": 5, "children": [{"id": 6, "children": [{"id": 7, "children": [{"ori_id": 59, "id": 8, "name": "drawer_front", "text": "drawer_front", "objs": ["original-7", "original-23", "original-1"]}, {"ori_id": 60, "id": 9, "name": "drawer_side", "text": "drawer_side", "objs": ["original-6"]}, {"ori_id": 61, "id": 10, "name": "drawer_side", "text": "drawer_side", "objs": ["original-10"]}, {"ori_id": 62, "id": 11, "name": "drawer_back", "text": "drawer_back", "objs": ["original-9", "original-4"]}, {"ori_id": 63, "id": 12, "name": "drawer_bottom", "text": "drawer_bottom", "objs": ["original-24", "original-8"]}], "name": "drawer_box", "text": "drawer_box", "ori_id": 48, "objs": ["original-7", "original-23", "original-1", "original-6", "original-10", "original-9", "original-4", "original-24", "original-8", "original-2"]}, {"ori_id": 49, "id": 13, "name": "handle", "text": "handle", "objs": ["original-17"]}], "name": "drawer", "text": "drawer", "ori_id": 40, "objs": ["original-7", "original-23", "original-1", "original-6", "original-10", "original-9", "original-4", "original-24", "original-8", "original-2", "original-17"]}, {"ori_id": 41, "id": 14, "name": "shelf", "text": "shelf", "objs": ["original-12", "original-13", "original-14"]}, {"ori_id": 42, "id": 15, "name": "vertical_side_panel", "text": "vertical_side_panel", "objs": ["original-27"]}, {"ori_id": 43, "id": 16, "name": "vertical_side_panel", "text": "vertical_side_panel", "objs": ["original-20"]}, {"ori_id": 44, "id": 17, "name": "leg", "text": "leg", "objs": ["original-19"]}, {"ori_id": 45, "id": 18, "name": "leg", "text": "leg", "objs": ["original-28"]}, {"ori_id": 46, "id": 19, "name": "leg", "text": "leg", "objs": ["original-21"]}, {"ori_id": 47, "id": 20, "name": "leg", "text": "leg", "objs": ["original-26"]}], "name": "drawer_base", "text": "drawer_base", "ori_id": 39, "objs": ["original-7", "original-23", "original-1", "original-6", "original-10", "original-9", "original-4", "original-24", "original-8", "original-2", "original-17", "original-12", "original-13", "original-14", "original-27", "original-20", "original-19", "original-28", "original-21", "original-26"]}], "name": "regular_table", "text": "regular_table", "ori_id": 37, "objs": ["original-3", "original-7", "original-23", "original-1", "original-6", "original-10", "original-9", "original-4", "original-24", "original-8", "original-2", "original-17", "original-12", "original-13", "original-14", "original-27", "original-20", "original-19", "original-28", "original-21", "original-26"]}], "name": "table", "text": "table", "ori_id": 0, "objs": ["original-3", "original-7", "original-23", "original-1", "original-6", "original-10", "original-9", "original-4", "original-24", "original-8", "original-2", "original-17", "original-12", "original-13", "original-14", "original-27", "original-20", "original-19", "original-28", "original-21", "original-26"]}]